{"name":": Interacción con el Cuadro de Texto","id":"pruebas-usuarios;:-interacción-con-el-cuadro-de-texto","testSteps":[{"number":1,"description":"Example: null","duration":28634,"startTime":"2024-10-15T01:45:37.208-05:00[America/Bogota]","screenshots":[{"screenshot":"d0b7054336421dd1bfc0cf4c438c66bf7c6bb05312183d764781644d8155c3cf.png","timeStamp":1728974765842}],"result":"SUCCESS","precondition":false,"level":0,"children":[{"number":2,"description":"Given navego en la aplicación","duration":14090,"startTime":"2024-10-15T01:45:37.213-05:00[America/Bogota]","screenshots":[{"screenshot":"1f64de4b47505e24590094e665fef032df33287586fe0a2ede5f16a868989c73.png","timeStamp":1728974751303}],"result":"SUCCESS","precondition":false,"level":1,"children":[{"number":3,"description":"Abrir web","duration":13790,"startTime":"2024-10-15T01:45:37.501-05:00[America/Bogota]","screenshots":[{"screenshot":"1f64de4b47505e24590094e665fef032df33287586fe0a2ede5f16a868989c73.png","timeStamp":1728974751288}],"result":"SUCCESS","precondition":false,"level":2}]},{"number":4,"description":"When ingreso a textBox y lleno el formulario \"Leonardo\" \"leonardoprueba@gmail.com\" \"Cr29 #19-38\" \"Cr29 #19-39\"","duration":8145,"startTime":"2024-10-15T01:45:51.303-05:00[America/Bogota]","screenshots":[{"screenshot":"1f64de4b47505e24590094e665fef032df33287586fe0a2ede5f16a868989c73.png","timeStamp":1728974751308},{"screenshot":"d0b7054336421dd1bfc0cf4c438c66bf7c6bb05312183d764781644d8155c3cf.png","timeStamp":1728974759448}],"result":"SUCCESS","precondition":false,"level":1,"children":[{"number":5,"description":"Seleccionar elements","duration":378,"startTime":"2024-10-15T01:45:51.311-05:00[America/Bogota]","screenshots":[{"screenshot":"1f64de4b47505e24590094e665fef032df33287586fe0a2ede5f16a868989c73.png","timeStamp":1728974751317},{"screenshot":"bb7a76d8c436cd6db6d5cfe669d328f9077c93e0764f0898abe0c3fc2f33ea1b.png","timeStamp":1728974751689}],"result":"SUCCESS","precondition":false,"level":2},{"number":6,"description":"Interacción text box: Leonardo, leonardoprueba@gmail.com, Cr29 #19-38, \"Cr29 #19-39\"","duration":7738,"startTime":"2024-10-15T01:45:51.694-05:00[America/Bogota]","screenshots":[{"screenshot":"bb7a76d8c436cd6db6d5cfe669d328f9077c93e0764f0898abe0c3fc2f33ea1b.png","timeStamp":1728974751703},{"screenshot":"d0b7054336421dd1bfc0cf4c438c66bf7c6bb05312183d764781644d8155c3cf.png","timeStamp":1728974759432}],"result":"SUCCESS","precondition":false,"level":2}]},{"number":7,"description":"Then valido la informacion ingresada \"Leonardo\" \"leonardoprueba@gmail.com\" \"Cr29 #19-38\" \"Cr29 #19-39\"","duration":6378,"startTime":"2024-10-15T01:45:59.448-05:00[America/Bogota]","screenshots":[{"screenshot":"d0b7054336421dd1bfc0cf4c438c66bf7c6bb05312183d764781644d8155c3cf.png","timeStamp":1728974759448},{"screenshot":"d0b7054336421dd1bfc0cf4c438c66bf7c6bb05312183d764781644d8155c3cf.png","timeStamp":1728974765826}],"result":"SUCCESS","precondition":false,"level":1,"children":[{"number":8,"description":"Validar informacion: Leonardo, leonardoprueba@gmail.com, Cr29 #19-38, Cr29 #19-39","duration":6378,"startTime":"2024-10-15T01:45:59.448-05:00[America/Bogota]","screenshots":[{"screenshot":"d0b7054336421dd1bfc0cf4c438c66bf7c6bb05312183d764781644d8155c3cf.png","timeStamp":1728974759463},{"screenshot":"d0b7054336421dd1bfc0cf4c438c66bf7c6bb05312183d764781644d8155c3cf.png","timeStamp":1728974765826}],"result":"SUCCESS","precondition":false,"level":2}]}]}],"userStory":{"id":"pruebas-usuarios","storyName":"Pruebas Usuarios","path":"src/test/resources/com.prueba.features/Escenarios.feature","type":"feature"},"featureTag":{"name":"Features/Pruebas Usuarios","type":"feature","displayName":"Features/Pruebas Usuarios"},"title":": Interacción con el Cuadro de Texto","tags":[{"name":"PruebasUsuarios","type":"tag","displayName":"PruebasUsuarios"},{"name":"CP001","type":"tag","displayName":"CP001"}],"startTime":"2024-10-15T01:45:37.145-05:00[America/Bogota]","duration":29429,"projectKey":"","isManualTestingUpToDate":false,"manual":false,"testSource":"Cucumber","result":"SUCCESS","scenarioOutline":"Given navego en la aplicación\r\nWhen ingreso a textBox y lleno el formulario \u003cNombre\u003e \u003cCorreo\u003e \u003cDireccionActual\u003e \u003cDireccionPermanente\u003e\r\nThen valido la informacion ingresada \u003cNombre\u003e \u003cCorreo\u003e \u003cDireccionActual\u003e \u003cDireccionPermanente\u003e"}